{
  "updated": "2026-06-01 19:39",
  "tracking": {
    "3340760021": {
      "status": "✅ 已送達",
      "status_cls": "done",
      "date": "2026/05/14"
    },
    "3332182394": {
      "status": "✅ 已送達",
      "status_cls": "done",
      "date": "2026/05/07"
    },
    "3349633151": {
      "status": "✅ 已送達",
      "status_cls": "done",
      "date": "2026/05/23"
    },
    "3360261612": {
      "status": "送達超商",
      "status_cls": "other",
      "date": "2026/06/01"
    },
    "3355512322": {
      "status": "✅ 已送達",
      "status_cls": "done",
      "date": "2026/05/27"
    },
    "3350470701": {
      "status": "✅ 已送達",
      "status_cls": "done",
      "date": "2026/05/22"
    },
    "3325798700": {
      "status": "✅ 已送達",
      "status_cls": "done",
      "date": "2026/04/30"
    },
    "3353538484": {
      "status": "✅ 已送達",
      "status_cls": "done",
      "date": "2026/05/26"
    },
    "3351932743": {
      "status": "✅ 已送達",
      "status_cls": "done",
      "date": "2026/05/25"
    },
    "3344411755": {
      "status": "✅ 已送達",
      "status_cls": "done",
      "date": "2026/05/21"
    },
    "3357247401": {
      "status": "✅ 已送達",
      "status_cls": "done",
      "date": "2026/05/28"
    },
    "3356252266": {
      "status": "✅ 已送達",
      "status_cls": "done",
      "date": "2026/05/28"
    },
    "3360261601": {
      "status": "✅ 已送達",
      "status_cls": "done",
      "date": "2026/05/31"
    },
    "3361109850": {
      "status": "✅ 已送達",
      "status_cls": "done",
      "date": "2026/06/01"
    },
    "3340759925": {
      "status": "✅ 已送達",
      "status_cls": "done",
      "date": "2026/05/14"
    },
    "3340769972": {
      "status": "✅ 已送達",
      "status_cls": "done",
      "date": "2026/05/15"
    },
    "3335997873": {
      "status": "✅ 已送達",
      "status_cls": "done",
      "date": "2026/05/11"
    },
    "3358774193": {
      "status": "✅ 已送達",
      "status_cls": "done",
      "date": "2026/05/29"
    },
    "3335408322": {
      "status": "✅ 已送達",
      "status_cls": "done",
      "date": "2026/05/11"
    },
    "3346297570": {
      "status": "✅ 已送達",
      "status_cls": "done",
      "date": "2026/05/19"
    },
    "3325553593": {
      "status": "✅ 已送達",
      "status_cls": "done",
      "date": "2026/04/30"
    },
    "3328108346": {
      "status": "✅ 已送達",
      "status_cls": "done",
      "date": "2026/05/06"
    },
    "3351136784": {
      "status": "✅ 已送達",
      "status_cls": "done",
      "date": "2026/05/22"
    },
    "3347624254": {
      "status": "✅ 已送達",
      "status_cls": "done",
      "date": "2026/05/20"
    },
    "3348933641": {
      "status": "✅ 已送達",
      "status_cls": "done",
      "date": "2026/05/25"
    },
    "3353538215": {
      "status": "✅ 已送達",
      "status_cls": "done",
      "date": "2026/05/27"
    },
    "3345383075": {
      "status": "✅ 已送達",
      "status_cls": "done",
      "date": "2026/05/20"
    },
    "3340759962": {
      "status": "✅ 已送達",
      "status_cls": "done",
      "date": "2026/05/14"
    },
    "C05375636000001": {
      "status": "查詢失敗",
      "status_cls": "error",
      "date": null
    },
    "T97771676000001": {
      "status": "查詢失敗",
      "status_cls": "error",
      "date": null
    },
    "C01576606000001": {
      "status": "查詢失敗",
      "status_cls": "error",
      "date": null
    },
    "C08458406000001": {
      "status": "查詢失敗",
      "status_cls": "error",
      "date": null
    },
    "C05375606000001": {
      "status": "查詢失敗",
      "status_cls": "error",
      "date": null
    },
    "T88994646000001": {
      "status": "查詢失敗",
      "status_cls": "error",
      "date": null
    },
    "T97771646000001": {
      "status": "查詢失敗",
      "status_cls": "error",
      "date": null
    },
    "T98264006000001": {
      "status": "查詢失敗",
      "status_cls": "error",
      "date": null
    },
    "T97771656000001": {
      "status": "查詢失敗",
      "status_cls": "error",
      "date": null
    },
    "C08458516000001": {
      "status": "查詢失敗",
      "status_cls": "error",
      "date": null
    },
    "16340657112": {
      "status": "查詢失敗",
      "status_cls": "error",
      "date": null
    },
    "16340506150": {
      "status": "查詢失敗",
      "status_cls": "error",
      "date": null
    },
    "16340681214": {
      "status": "查詢失敗",
      "status_cls": "error",
      "date": null
    },
    "16340408083": {
      "status": "查詢失敗",
      "status_cls": "error",
      "date": null
    },
    "3361867622": {
      "status": "轉運中",
      "status_cls": "other",
      "date": "2026/06/02"
    },
    "3363089214": {
      "status": "轉運中",
      "status_cls": "other",
      "date": "2026/06/02"
    },
    "C20472206000001": {
      "status": "查詢失敗",
      "status_cls": "error",
      "date": null
    },
    "C19535086000001": {
      "status": "查詢失敗",
      "status_cls": "error",
      "date": null
    },
    "C19535106000001": {
      "status": "查詢失敗",
      "status_cls": "error",
      "date": null
    },
    "C19535076000001": {
      "status": "查詢失敗",
      "status_cls": "error",
      "date": null
    },
    "C19535146000001": {
      "status": "查詢失敗",
      "status_cls": "error",
      "date": null
    },
    "16340857651": {
      "status": "查詢失敗",
      "status_cls": "error",
      "date": null
    },
    "16340856896": {
      "status": "查詢失敗",
      "status_cls": "error",
      "date": null
    }
  }
}